RAM/RAM.sv
/*
Author: Tobias Markus

initiation template
RAM #(        
        .DEPTH(),
        .WIDTH(),
        .INIT_FILE()
    )
RAM_I (
        .clk(),        
        .enable(),
        .wr_en(),
        .address(),
        .data_in(),
        .data_out()
    );
*/

module RAM
    #(
        parameter DEPTH = 4,
        parameter WIDTH = 8,
        parameter INIT_FILE = "data.dat"
    )
    (
        input logic clk,
        input logic enable,
        input logic wr_en,
        input logic[DEPTH-1:0] address,
        input logic[WIDTH-1:0] data_in,
        output logic[WIDTH-1:0] data_out
    );

    logic[WIDTH-1:0] memory [0:2**DEPTH-1];
    
    // init RAM
    initial
    begin
        $readmemh(INIT_FILE, memory) ;
    end

    // control and data path
    always @(posedge clk) // synchronous reset
    begin
        if(enable)
        begin
            if (wr_en)
            begin
                memory[address] <= data_in;
            end
            else
            begin
                data_out <= memory[address];
            end
        end
    end

endmodule

common/clk_gen.v
//Authors: Sebastian Wittka, Tobias Markus
module clk_gen #(
    	parameter period =10
    )
   	(
   		output reg clk_out=0
   	);

	always
	begin
	    #(period/2) clk_out <= ~clk_out;
	end

endmodule

RAM/RAM_tb.v
module RAM_tb ();
	
	parameter WIDTH = 8;
	parameter DEPTH = 4;
	parameter PERIOD = 10;

	wire clk;
	reg enable;
	reg wr_en;
	reg[DEPTH-1:0] address;
	reg[WIDTH-1:0] data_in;
	wire[WIDTH-1:0] data_out;
	
	clk_gen #(.period(PERIOD)) clk_gen_I (.clk_out(clk));
	
	RAM #(	.DEPTH(DEPTH),
			.WIDTH(WIDTH)
	) 
	RAM_I (
			.clk(clk),	
			.enable(enable),
			.wr_en(wr_en),
			.address(address),
			.data_in(data_in),
			.data_out(data_out)
	);

	initial 
	begin
		$dumpfile("RAM.vcd");
    	$dumpvars(0,RAM_tb);
		enable <= 1;
		wr_en 	<= 1'b0;
		#100
		address <= 0;
		#20
		address <= 1;
		#20
		address <= 2;
		#20
		address <= 3;
		#20
		address <= 4;
		#20
		address <= 5;
		wr_en <= 1'b1;
		data_in <= 8'hff;
		#20
		address <= 5;
		wr_en <= 1'b0;
		#20 
		$stop;
	end

endmodule

RAM/RAM.vcd
$date
	Thu Jan 23 23:00:31 2014
$end
$version
	Icarus Verilog
$end
$timescale
	1s
$end
$scope module RAM_tb $end
$var wire 1 ! clk $end
$var wire 8 " data_out [7:0] $end
$var reg 4 # address [3:0] $end
$var reg 8 $ data_in [7:0] $end
$var reg 1 % enable $end
$var reg 1 & wr_en $end
$scope module clk_gen_I $end
$var reg 1 ' clk_out $end
$upscope $end
$scope module RAM_I $end
$var wire 4 ( address [3:0] $end
$var wire 1 ! clk $end
$var wire 8 ) data_in [7:0] $end
$var wire 1 * enable $end
$var wire 1 + wr_en $end
$var reg 8 , data_out [7:0] $end
$upscope $end
$upscope $end
$enddefinitions $end
#0
$dumpvars
bx ,
0+
1*
bx )
bx (
0'
0&
1%
bx $
bx #
bx "
0!
$end
#5
1'
1!
#10
0'
0!
#15
1'
1!
#20
0'
0!
#25
1'
1!
#30
0'
0!
#35
1'
1!
#40
0'
0!
#45
1'
1!
#50
0'
0!
#55
1'
1!
#60
0'
0!
#65
1'
1!
#70
0'
0!
#75
1'
1!
#80
0'
0!
#85
1'
1!
#90
0'
0!
#95
1'
1!
#100
0'
0!
b0 #
b0 (
#105
b0 ,
b0 "
1'
1!
#110
0'
0!
#115
1'
1!
#120
0'
0!
b1 #
b1 (
#125
b1 ,
b1 "
1'
1!
#130
0'
0!
#135
1'
1!
#140
0'
0!
b10 #
b10 (
#145
b10 ,
b10 "
1'
1!
#150
0'
0!
#155
1'
1!
#160
0'
0!
b11 #
b11 (
#165
b11 ,
b11 "
1'
1!
#170
0'
0!
#175
1'
1!
#180
0'
0!
b100 #
b100 (
#185
b100 ,
b100 "
1'
1!
#190
0'
0!
#195
1'
1!
#200
0'
0!
b11111111 $
b11111111 )
1&
1+
b101 #
b101 (
#205
1'
1!
#210
0'
0!
#215
1'
1!
#220
0'
0!
0&
0+
#225
b11111111 ,
b11111111 "
1'
1!
